project_mail/__init__.py
project_mail/smail.py
project_mail-0.0.1.dist-info/METADATA
project_mail-0.0.1.dist-info/WHEEL
project_mail-0.0.1.dist-info/licenses/LICENSE
project_mail-0.0.1.dist-info/RECORD
